{"Errors":[],"HasErrors":false,"BatchedResultsOrder":["q1","q0"],"TotalRequests":2,"BatchedResults":{"q1":{"Id":"q1","Limit":10,"Offset":0,"TotalResults":44,"Locale":"en_US","Results":[{"Id":"201622905","CID":"6a9c8ee2-a3db-5687-a9f7-6fa9969843cb","SourceClient":"gap","Badges":{"incentivizedReview":{"ContentType":"REVIEW","Id":"incentivizedReview","BadgeType":"Custom"}},"BadgesOrder":["incentivizedReview"],"LastModeratedTime":"2018-07-27T22:00:30.000+00:00","LastModificationTime":"2018-07-27T22:00:30.000+00:00","ProductId":"205434012","CampaignId":"online","AuthorId":"aiggomw1u9u1x2x6cbn5odfdo","ContentLocale":"en_US","IsFeatured":false,"TotalClientResponseCount":0,"TotalCommentCount":0,"Rating":2,"IsRatingsOnly":false,"TotalFeedbackCount":0,"TotalNegativeFeedbackCount":0,"TotalPositiveFeedbackCount":0,"ModerationStatus":"APPROVED","SubmissionId":"qeu4mbqui0tm7sne19thhsyuv","SubmissionTime":"2018-07-27T21:35:54.000+00:00","ReviewText":"The glasses are ok, not as solid as I would want. Will be returning them","Title":"Just ok","UserNickname":"DRSWIM","UserLocation":null,"Cons":null,"TagDimensions":{},"SecondaryRatingsOrder":[],"IsRecommended":null,"TagDimensionsOrder":[],"Videos":[],"Pros":null,"RatingRange":5,"SecondaryRatings":{},"ContextDataValuesOrder":[],"IsSyndicated":false,"CommentIds":[],"Photos":[],"ProductRecommendationIds":[],"ClientResponses":[],"Helpfulness":null,"AdditionalFields":{},"ContextDataValues":{},"AdditionalFieldsOrder":[]},{"Id":"201439954","CID":"bef64762-855f-5910-96bb-27a0cece0723","SourceClient":"gap","Badges":{"incentivizedReview":{"ContentType":"REVIEW","Id":"incentivizedReview","BadgeType":"Custom"}},"BadgesOrder":["incentivizedReview"],"LastModeratedTime":"2018-07-23T23:00:11.000+00:00","LastModificationTime":"2018-07-23T23:00:11.000+00:00","ProductId":"205434012","CampaignId":"online2","AuthorId":"6t395zv4ggp2k123pq59z0mw2","ContentLocale":"en_US","IsFeatured":false,"TotalClientResponseCount":0,"TotalCommentCount":0,"Rating":5,"IsRatingsOnly":false,"TotalFeedbackCount":0,"TotalNegativeFeedbackCount":0,"TotalPositiveFeedbackCount":0,"ModerationStatus":"APPROVED","SubmissionId":"ag3yyo77c3b97m191al8o0arv","SubmissionTime":"2018-07-23T22:32:09.000+00:00","ReviewText":"I got these for my husband and he loved them! They look great!! The only downside was he didn\u2019t like being able to see out the side of them but that\u2019s just a preference that he has!","Title":"Love them!","UserNickname":"Kristina","UserLocation":null,"Cons":null,"TagDimensions":{},"SecondaryRatingsOrder":[],"IsRecommended":null,"TagDimensionsOrder":[],"Videos":[],"Pros":null,"RatingRange":5,"SecondaryRatings":{},"ContextDataValuesOrder":[],"IsSyndicated":false,"CommentIds":[],"Photos":[],"ProductRecommendationIds":[],"ClientResponses":[],"Helpfulness":null,"AdditionalFields":{},"ContextDataValues":{},"AdditionalFieldsOrder":[]},{"Id":"201424644","CID":"c639ece2-0f11-5a4b-b9da-c6690c4a0e75","SourceClient":"gap","Badges":{"incentivizedReview":{"ContentType":"REVIEW","Id":"incentivizedReview","BadgeType":"Custom"}},"BadgesOrder":["incentivizedReview"],"LastModeratedTime":"2018-07-23T13:32:00.000+00:00","LastModificationTime":"2018-07-23T13:32:00.000+00:00","ProductId":"205434012","CampaignId":"instore","AuthorId":"2y5ed8gz3j5wmevyph00mulkw","ContentLocale":"en_US","IsFeatured":false,"TotalClientResponseCount":0,"TotalCommentCount":0,"Rating":4,"IsRatingsOnly":false,"TotalFeedbackCount":0,"TotalNegativeFeedbackCount":0,"TotalPositiveFeedbackCount":0,"ModerationStatus":"APPROVED","SubmissionId":"bb048i06i3nd3gdwn60u5103f","SubmissionTime":"2018-07-23T13:08:30.000+00:00","ReviewText":"Great deal on these shades! Got them 1/2 off-good for running","UserNickname":"Aimee","UserLocation":null,"Cons":null,"TagDimensions":{},"SecondaryRatingsOrder":[],"IsRecommended":null,"TagDimensionsOrder":[],"Videos":[],"Pros":null,"RatingRange":5,"SecondaryRatings":{},"ContextDataValuesOrder":[],"IsSyndicated":false,"CommentIds":[],"Photos":[],"Title":null,"ProductRecommendationIds":[],"ClientResponses":[],"Helpfulness":null,"AdditionalFields":{},"ContextDataValues":{},"AdditionalFieldsOrder":[]},{"Id":"201321858","CID":"ab837c57-cc55-5f87-bc33-aede4cce9858","SourceClient":"gap","Badges":{"incentivizedReview":{"ContentType":"REVIEW","Id":"incentivizedReview","BadgeType":"Custom"}},"BadgesOrder":["incentivizedReview"],"LastModeratedTime":"2018-07-19T09:17:29.000+00:00","LastModificationTime":"2018-07-19T09:17:29.000+00:00","ProductId":"205434012","CampaignId":"instore","AuthorId":"2z1qcs90l4n47jg6tockm6gr7","ContentLocale":"en_US","IsFeatured":false,"TotalClientResponseCount":0,"TotalCommentCount":0,"Rating":5,"IsRatingsOnly":false,"TotalFeedbackCount":0,"TotalNegativeFeedbackCount":0,"TotalPositiveFeedbackCount":0,"ModerationStatus":"APPROVED","SubmissionId":"3gzsplv7aktjst87h8wtj1125","SubmissionTime":"2018-07-19T04:26:20.000+00:00","ReviewText":"Amazing sunglasses my husband is happy with them !!","UserNickname":"Vero","UserLocation":null,"Cons":null,"TagDimensions":{},"SecondaryRatingsOrder":[],"IsRecommended":null,"TagDimensionsOrder":[],"Videos":[],"Pros":null,"RatingRange":5,"SecondaryRatings":{},"ContextDataValuesOrder":[],"IsSyndicated":false,"CommentIds":[],"Photos":[],"Title":null,"ProductRecommendationIds":[],"ClientResponses":[],"Helpfulness":null,"AdditionalFields":{},"ContextDataValues":{},"AdditionalFieldsOrder":[]},{"Id":"201198506","CID":"4a96a194-7078-51f9-992d-a8381ecd7628","SourceClient":"gap","LastModeratedTime":"2018-07-14T14:15:23.000+00:00","LastModificationTime":"2018-07-14T14:15:23.000+00:00","ProductId":"205434012","UserLocation":"Delaware","AuthorId":"62u4k7jxygii6ykb93n5eg0r3","ContentLocale":"en_US","IsFeatured":false,"TotalClientResponseCount":0,"TotalCommentCount":0,"Rating":5,"IsRatingsOnly":false,"TotalFeedbackCount":0,"TotalNegativeFeedbackCount":0,"TotalPositiveFeedbackCount":0,"ModerationStatus":"APPROVED","SubmissionId":"iagqe86f6sp8ylbi9o7slmjpm","SubmissionTime":"2018-07-14T13:50:33.000+00:00","TagDimensionsOrder":["OnMensEndUse"],"ReviewText":"I got these sunglasses for  my son and he loves them. He is going to get another pair when his current pair gets either a scratch on the lens or misplaced.","UserNickname":"TrayDiva","TagDimensions":{"OnMensEndUse":{"Values":["Casual/Everyday"],"Id":"OnMensEndUse","Label":null}},"BadgesOrder":[],"Cons":null,"SecondaryRatingsOrder":[],"IsRecommended":null,"Videos":[],"Pros":null,"RatingRange":5,"SecondaryRatings":{},"ContextDataValuesOrder":[],"IsSyndicated":false,"CommentIds":[],"Photos":[],"Title":null,"ProductRecommendationIds":[],"ClientResponses":[],"Helpfulness":null,"AdditionalFields":{},"Badges":{},"ContextDataValues":{},"AdditionalFieldsOrder":[],"CampaignId":null},{"Id":"201137171","CID":"c0ec5f27-8887-57b9-adcd-41f8d868c617","SourceClient":"gap","Badges":{"incentivizedReview":{"ContentType":"REVIEW","Id":"incentivizedReview","BadgeType":"Custom"}},"BadgesOrder":["incentivizedReview"],"LastModeratedTime":"2018-07-12T02:31:30.000+00:00","LastModificationTime":"2018-07-12T02:31:30.000+00:00","ProductId":"205434012","CampaignId":"instore2","AuthorId":"qe5q7mh5nsafe4b5zfxxlg64v","ContentLocale":"en_US","IsFeatured":false,"TotalClientResponseCount":0,"TotalCommentCount":0,"Rating":5,"IsRatingsOnly":false,"TotalFeedbackCount":0,"TotalNegativeFeedbackCount":0,"TotalPositiveFeedbackCount":0,"ModerationStatus":"APPROVED","SubmissionId":"lgnomqr9y119h0hikl41qq983","SubmissionTime":"2018-07-12T02:02:37.000+00:00","ReviewText":"My husband absolutely love these shades. He wears them everyday.","UserNickname":"Cb","UserLocation":null,"Cons":null,"TagDimensions":{},"SecondaryRatingsOrder":[],"IsRecommended":null,"TagDimensionsOrder":[],"Videos":[],"Pros":null,"RatingRange":5,"SecondaryRatings":{},"ContextDataValuesOrder":[],"IsSyndicated":false,"CommentIds":[],"Photos":[],"Title":null,"ProductRecommendationIds":[],"ClientResponses":[],"Helpfulness":null,"AdditionalFields":{},"ContextDataValues":{},"AdditionalFieldsOrder":[]},{"Id":"201108236","CID":"8cb83afc-3937-57f5-a75a-3f84e7a86745","SourceClient":"gap","Badges":{"incentivizedReview":{"ContentType":"REVIEW","Id":"incentivizedReview","BadgeType":"Custom"}},"BadgesOrder":["incentivizedReview"],"LastModeratedTime":"2018-07-11T00:00:34.000+00:00","LastModificationTime":"2018-07-11T00:00:34.000+00:00","ProductId":"205434002","CampaignId":"online","AuthorId":"77khuatdrl5iaxnrs4r2jza3b","ContentLocale":"en_US","IsFeatured":false,"TotalClientResponseCount":0,"TotalCommentCount":0,"Rating":5,"IsRatingsOnly":false,"TotalFeedbackCount":0,"TotalNegativeFeedbackCount":0,"TotalPositiveFeedbackCount":0,"ModerationStatus":"APPROVED","SubmissionId":"u9o5ow08n1jw82khbpwe5ipdm","SubmissionTime":"2018-07-10T23:35:41.000+00:00","ReviewText":"I purchased these for my husband who somehow breaks every pair he has ever owned. He hasn\u2019t broken these yet! Seem to be the perfect pair for him.","Title":"Sunglasses","UserNickname":"Mel","UserLocation":null,"Cons":null,"TagDimensions":{},"SecondaryRatingsOrder":[],"IsRecommended":null,"TagDimensionsOrder":[],"Videos":[],"Pros":null,"RatingRange":5,"SecondaryRatings":{},"ContextDataValuesOrder":[],"IsSyndicated":false,"CommentIds":[],"Photos":[],"ProductRecommendationIds":[],"ClientResponses":[],"Helpfulness":null,"AdditionalFields":{},"ContextDataValues":{},"AdditionalFieldsOrder":[]},{"Id":"201093350","CID":"705338ac-7834-5b89-8115-38e101780354","SourceClient":"gap","Badges":{"incentivizedReview":{"ContentType":"REVIEW","Id":"incentivizedReview","BadgeType":"Custom"}},"BadgesOrder":["incentivizedReview"],"LastModeratedTime":"2018-07-10T13:00:59.000+00:00","LastModificationTime":"2018-07-10T13:00:59.000+00:00","ProductId":"205434012","CampaignId":"online","AuthorId":"smmfthok4rjpfearkyaxve1ls","ContentLocale":"en_US","IsFeatured":false,"TotalClientResponseCount":0,"TotalCommentCount":0,"Rating":5,"IsRatingsOnly":false,"TotalFeedbackCount":0,"TotalNegativeFeedbackCount":0,"TotalPositiveFeedbackCount":0,"ModerationStatus":"APPROVED","SubmissionId":"7b94maafk02zisolzii744fo3","SubmissionTime":"2018-07-10T12:32:25.000+00:00","ReviewText":"Did not expect these to have mirrored lenses, but they are cute. A bit bigger than the traditional wayfarer style glasses. Bought them for my son to see how he would care for a pair of sunglasses, but for the money I was surprised at how sturdy these feel!","Title":"Cute for the money!","UserNickname":"handgsmom","UserLocation":null,"Cons":null,"TagDimensions":{},"SecondaryRatingsOrder":[],"IsRecommended":null,"TagDimensionsOrder":[],"Videos":[],"Pros":null,"RatingRange":5,"SecondaryRatings":{},"ContextDataValuesOrder":[],"IsSyndicated":false,"CommentIds":[],"Photos":[],"ProductRecommendationIds":[],"ClientResponses":[],"Helpfulness":null,"AdditionalFields":{},"ContextDataValues":{},"AdditionalFieldsOrder":[]},{"Id":"200962424","CID":"a87e0882-8a1e-5d95-9f6a-72010b747f85","SourceClient":"gap","Badges":{"incentivizedReview":{"ContentType":"REVIEW","Id":"incentivizedReview","BadgeType":"Custom"}},"BadgesOrder":["incentivizedReview"],"LastModeratedTime":"2018-07-05T13:01:14.000+00:00","LastModificationTime":"2018-07-05T13:01:14.000+00:00","ProductId":"205434002","CampaignId":"online","AuthorId":"aaggas0cameq9f7ohzs0h8arc","ContentLocale":"en_US","IsFeatured":false,"TotalClientResponseCount":0,"TotalCommentCount":0,"Rating":5,"IsRatingsOnly":false,"TotalFeedbackCount":0,"TotalNegativeFeedbackCount":0,"TotalPositiveFeedbackCount":0,"ModerationStatus":"APPROVED","SubmissionId":"2jre4ms6myb82x2h83skmpyoc","SubmissionTime":"2018-07-05T12:39:06.000+00:00","ReviewText":"These look great! I would recommend these sunglasses!","UserNickname":"Irmss","UserLocation":null,"Cons":null,"TagDimensions":{},"SecondaryRatingsOrder":[],"IsRecommended":null,"TagDimensionsOrder":[],"Videos":[],"Pros":null,"RatingRange":5,"SecondaryRatings":{},"ContextDataValuesOrder":[],"IsSyndicated":false,"CommentIds":[],"Photos":[],"Title":null,"ProductRecommendationIds":[],"ClientResponses":[],"Helpfulness":null,"AdditionalFields":{},"ContextDataValues":{},"AdditionalFieldsOrder":[]},{"Id":"200916358","CID":"92819427-dc49-593c-bff3-b7b9c32c3d22","SourceClient":"gap","Badges":{"incentivizedReview":{"ContentType":"REVIEW","Id":"incentivizedReview","BadgeType":"Custom"}},"BadgesOrder":["incentivizedReview"],"LastModeratedTime":"2018-07-03T15:30:33.000+00:00","LastModificationTime":"2018-07-03T15:30:33.000+00:00","ProductId":"205434002","CampaignId":"online","AuthorId":"tusc7uv87cctc7sra0ukq8oq7","ContentLocale":"en_US","IsFeatured":false,"TotalClientResponseCount":0,"TotalCommentCount":0,"Rating":5,"IsRatingsOnly":false,"TotalFeedbackCount":0,"TotalNegativeFeedbackCount":0,"TotalPositiveFeedbackCount":0,"ModerationStatus":"APPROVED","SubmissionId":"dmdbvfpm9yi0sl8gt0a8brsw4","SubmissionTime":"2018-07-03T15:00:52.000+00:00","ReviewText":"I am a female but I love these 'mens' glasses. They are stylish and comfortable, I like that they flex outward as well for a comfortable fit.","Title":"Comfortable and nice","UserNickname":"jma5012","UserLocation":null,"Cons":null,"TagDimensions":{},"SecondaryRatingsOrder":[],"IsRecommended":null,"TagDimensionsOrder":[],"Videos":[],"Pros":null,"RatingRange":5,"SecondaryRatings":{},"ContextDataValuesOrder":[],"IsSyndicated":false,"CommentIds":[],"Photos":[],"ProductRecommendationIds":[],"ClientResponses":[],"Helpfulness":null,"AdditionalFields":{},"ContextDataValues":{},"AdditionalFieldsOrder":[]}],"Includes":{"Products":{"205434012":{"FamilyIds":["205434"],"AttributesOrder":["SEASON_YEAR","SEASON_CODE","BV_FE_EXPAND","BV_FE_FAMILY"],"Attributes":{"SEASON_YEAR":{"Id":"SEASON_YEAR","Values":[{"Value":"2018","Locale":null}]},"SEASON_CODE":{"Id":"SEASON_CODE","Values":[{"Value":"M07","Locale":null}]},"BV_FE_EXPAND":{"Id":"BV_FE_EXPAND","Values":[{"Value":"BV_FE_FAMILY:205434","Locale":null}]},"BV_FE_FAMILY":{"Id":"BV_FE_FAMILY","Values":[{"Value":"205434","Locale":null}]}},"Description":"Classic Sunglasses for Men","ImageUrl":"http://oldnavy.gap.com/resources/productImage/v1/205434012/VI","Name":"Classic Sunglasses for Men  (Gray)","Id":"205434012","CategoryId":"205434","BrandExternalId":"3","Brand":{"Id":"3","Name":"OLD NAVY"},"Active":true,"ProductPageUrl":"http://oldnavy.gap.com/browse/product.do?pid=205434012&locale=en_US","Disabled":false,"StoryIds":[],"EANs":[],"ManufacturerPartNumbers":[],"QuestionIds":[],"UPCs":[],"ISBNs":[],"ReviewIds":[],"ModelNumbers":[],"ReviewStatistics":{"NotHelpfulVoteCount":0,"TotalReviewCount":52,"RecommendedCount":0,"FirstSubmissionTime":"2018-03-06T03:48:36.000+00:00","LastSubmissionTime":"2018-08-05T02:02:52.000+00:00","NotRecommendedCount":0,"RatingsOnlyReviewCount":8,"RatingDistribution":[{"RatingValue":5,"Count":37},{"RatingValue":4,"Count":9},{"RatingValue":1,"Count":2},{"RatingValue":2,"Count":2},{"RatingValue":3,"Count":2}],"HelpfulVoteCount":3,"FeaturedReviewCount":0,"AverageOverallRating":4.480769230769231,"ContextDataDistributionOrder":["IncentivizedReview"],"ContextDataDistribution":{"IncentivizedReview":{"Id":"IncentivizedReview","Values":[{"Count":48,"Value":"True"}]}},"SecondaryRatingsAveragesOrder":[],"TagDistributionOrder":[],"SecondaryRatingsAverages":{},"TagDistribution":{},"OverallRatingRange":5},"TotalReviewCount":52,"FilteredReviewStatistics":{"NotHelpfulVoteCount":0,"TotalReviewCount":44,"RecommendedCount":0,"FirstSubmissionTime":"2018-03-06T03:48:36.000+00:00","LastSubmissionTime":"2018-07-27T21:35:54.000+00:00","NotRecommendedCount":0,"RatingsOnlyReviewCount":0,"RatingDistribution":[{"RatingValue":5,"Count":30},{"RatingValue":4,"Count":9},{"RatingValue":1,"Count":2},{"RatingValue":2,"Count":2},{"RatingValue":3,"Count":1}],"HelpfulVoteCount":3,"FeaturedReviewCount":0,"AverageOverallRating":4.431818181818182,"ContextDataDistributionOrder":["IncentivizedReview"],"ContextDataDistribution":{"IncentivizedReview":{"Id":"IncentivizedReview","Values":[{"Count":40,"Value":"True"}]}},"SecondaryRatingsAveragesOrder":[],"TagDistributionOrder":[],"SecondaryRatingsAverages":{},"TagDistribution":{},"OverallRatingRange":5}},"205434002":{"FamilyIds":["205434"],"AttributesOrder":["SEASON_YEAR","SEASON_CODE","BV_FE_EXPAND","BV_FE_FAMILY"],"Attributes":{"SEASON_YEAR":{"Id":"SEASON_YEAR","Values":[{"Value":"2018","Locale":null}]},"SEASON_CODE":{"Id":"SEASON_CODE","Values":[{"Value":"M07","Locale":null}]},"BV_FE_EXPAND":{"Id":"BV_FE_EXPAND","Values":[{"Value":"BV_FE_FAMILY:205434","Locale":null}]},"BV_FE_FAMILY":{"Id":"BV_FE_FAMILY","Values":[{"Value":"205434","Locale":null}]}},"Description":"Classic Sunglasses for Men","ImageUrl":"http://oldnavy.gap.com/resources/productImage/v1/205434002/VI","Name":"Classic Sunglasses for Men  (Blackjack)","Id":"205434002","CategoryId":"205434","BrandExternalId":"3","Brand":{"Id":"3","Name":"OLD NAVY"},"Active":true,"ProductPageUrl":"http://oldnavy.gap.com/browse/product.do?pid=205434002&locale=en_US","Disabled":false,"StoryIds":[],"EANs":[],"ManufacturerPartNumbers":[],"QuestionIds":[],"UPCs":[],"ISBNs":[],"ReviewIds":[],"ModelNumbers":[],"ReviewStatistics":{"AverageOverallRating":4.480769230769231,"NotHelpfulVoteCount":0,"TotalReviewCount":52,"ContextDataDistributionOrder":["IncentivizedReview"],"ContextDataDistribution":{"IncentivizedReview":{"Id":"IncentivizedReview","Values":[{"Count":48,"Value":"True"}]}},"RatingsOnlyReviewCount":8,"FeaturedReviewCount":0,"FirstSubmissionTime":"2018-03-06T03:48:36.000+00:00","LastSubmissionTime":"2018-08-05T02:02:52.000+00:00","NotRecommendedCount":0,"RatingDistribution":[{"RatingValue":5,"Count":37},{"RatingValue":4,"Count":9},{"RatingValue":1,"Count":2},{"RatingValue":2,"Count":2},{"RatingValue":3,"Count":2}],"RecommendedCount":0,"HelpfulVoteCount":3,"SecondaryRatingsAveragesOrder":[],"TagDistributionOrder":[],"SecondaryRatingsAverages":{},"TagDistribution":{},"OverallRatingRange":5},"TotalReviewCount":52,"FilteredReviewStatistics":{"AverageOverallRating":4.431818181818182,"NotHelpfulVoteCount":0,"TotalReviewCount":44,"ContextDataDistributionOrder":["IncentivizedReview"],"ContextDataDistribution":{"IncentivizedReview":{"Id":"IncentivizedReview","Values":[{"Count":40,"Value":"True"}]}},"RatingsOnlyReviewCount":0,"FeaturedReviewCount":0,"FirstSubmissionTime":"2018-03-06T03:48:36.000+00:00","LastSubmissionTime":"2018-07-27T21:35:54.000+00:00","NotRecommendedCount":0,"RatingDistribution":[{"RatingValue":5,"Count":30},{"RatingValue":4,"Count":9},{"RatingValue":1,"Count":2},{"RatingValue":2,"Count":2},{"RatingValue":3,"Count":1}],"RecommendedCount":0,"HelpfulVoteCount":3,"SecondaryRatingsAveragesOrder":[],"TagDistributionOrder":[],"SecondaryRatingsAverages":{},"TagDistribution":{},"OverallRatingRange":5}}},"ProductsOrder":["205434012","205434002"],"Authors":{"aaggas0cameq9f7ohzs0h8arc":{"Id":"aaggas0cameq9f7ohzs0h8arc","ContributorRank":"NONE","UserNickname":"Irmss","LastModeratedTime":"2018-07-05T13:01:15.000+00:00","ModerationStatus":"APPROVED","SubmissionTime":"2018-07-05T12:38:24.000+00:00","ThirdPartyIds":[],"Location":null,"ContextDataValuesOrder":[],"Avatar":{},"ContextDataValues":{},"ProductRecommendationIds":[],"CommentIds":[],"StoryIds":[],"QuestionIds":[],"ReviewIds":[],"Badges":{},"AdditionalFields":{},"Photos":[],"SecondaryRatings":{},"SecondaryRatingsOrder":[],"SubmissionId":null,"BadgesOrder":[],"AdditionalFieldsOrder":[],"Videos":[],"AnswerIds":[],"ReviewStatistics":{"RecommendedCount":0,"NotRecommendedCount":0,"FirstSubmissionTime":"2018-07-05T12:38:24.000+00:00","LastSubmissionTime":"2018-07-05T12:39:06.000+00:00","NotHelpfulVoteCount":0,"TotalReviewCount":2,"RatingDistribution":[{"RatingValue":5,"Count":2}],"RatingsOnlyReviewCount":0,"FeaturedReviewCount":0,"AverageOverallRating":5.0,"HelpfulVoteCount":0,"ContextDataDistribution":{},"ContextDataDistributionOrder":[],"SecondaryRatingsAveragesOrder":[],"TagDistributionOrder":[],"SecondaryRatingsAverages":{},"TagDistribution":{},"OverallRatingRange":5},"TotalReviewCount":2,"FilteredReviewStatistics":{"RecommendedCount":0,"NotRecommendedCount":0,"FirstSubmissionTime":"2018-07-05T12:39:06.000+00:00","LastSubmissionTime":"2018-07-05T12:39:06.000+00:00","NotHelpfulVoteCount":0,"TotalReviewCount":1,"RatingDistribution":[{"RatingValue":5,"Count":1}],"RatingsOnlyReviewCount":0,"FeaturedReviewCount":0,"AverageOverallRating":5.0,"HelpfulVoteCount":0,"ContextDataDistribution":{},"ContextDataDistributionOrder":[],"SecondaryRatingsAveragesOrder":[],"TagDistributionOrder":[],"SecondaryRatingsAverages":{},"TagDistribution":{},"OverallRatingRange":5}},"qe5q7mh5nsafe4b5zfxxlg64v":{"Id":"qe5q7mh5nsafe4b5zfxxlg64v","ContributorRank":"NONE","UserNickname":"Cb","LastModeratedTime":"2018-07-12T02:31:30.000+00:00","ModerationStatus":"APPROVED","SubmissionTime":"2018-07-12T02:01:34.000+00:00","ThirdPartyIds":[],"Location":null,"ContextDataValuesOrder":[],"Avatar":{},"ContextDataValues":{},"ProductRecommendationIds":[],"CommentIds":[],"StoryIds":[],"QuestionIds":[],"ReviewIds":[],"Badges":{},"AdditionalFields":{},"Photos":[],"SecondaryRatings":{},"SecondaryRatingsOrder":[],"SubmissionId":null,"BadgesOrder":[],"AdditionalFieldsOrder":[],"Videos":[],"AnswerIds":[],"ReviewStatistics":{"RatingDistribution":[{"RatingValue":5,"Count":5}],"FirstSubmissionTime":"2018-07-12T02:01:34.000+00:00","LastSubmissionTime":"2018-07-12T02:04:11.000+00:00","NotHelpfulVoteCount":0,"RatingsOnlyReviewCount":0,"RecommendedCount":0,"NotRecommendedCount":0,"FeaturedReviewCount":0,"AverageOverallRating":5.0,"HelpfulVoteCount":0,"TotalReviewCount":5,"ContextDataDistribution":{},"ContextDataDistributionOrder":[],"SecondaryRatingsAveragesOrder":[],"TagDistributionOrder":[],"SecondaryRatingsAverages":{},"TagDistribution":{},"OverallRatingRange":5},"TotalReviewCount":5,"FilteredReviewStatistics":{"RatingDistribution":[{"RatingValue":5,"Count":1}],"FirstSubmissionTime":"2018-07-12T02:02:37.000+00:00","LastSubmissionTime":"2018-07-12T02:02:37.000+00:00","NotHelpfulVoteCount":0,"RatingsOnlyReviewCount":0,"RecommendedCount":0,"NotRecommendedCount":0,"FeaturedReviewCount":0,"AverageOverallRating":5.0,"HelpfulVoteCount":0,"TotalReviewCount":1,"ContextDataDistribution":{},"ContextDataDistributionOrder":[],"SecondaryRatingsAveragesOrder":[],"TagDistributionOrder":[],"SecondaryRatingsAverages":{},"TagDistribution":{},"OverallRatingRange":5}},"6t395zv4ggp2k123pq59z0mw2":{"Id":"6t395zv4ggp2k123pq59z0mw2","ContributorRank":"NONE","UserNickname":"Kristina","LastModeratedTime":"2018-07-23T23:00:11.000+00:00","ModerationStatus":"APPROVED","SubmissionTime":"2018-07-23T22:32:09.000+00:00","ThirdPartyIds":[],"Location":null,"ContextDataValuesOrder":[],"Avatar":{},"ContextDataValues":{},"ProductRecommendationIds":[],"CommentIds":[],"StoryIds":[],"QuestionIds":[],"ReviewIds":[],"Badges":{},"AdditionalFields":{},"Photos":[],"SecondaryRatings":{},"SecondaryRatingsOrder":[],"SubmissionId":null,"BadgesOrder":[],"AdditionalFieldsOrder":[],"Videos":[],"AnswerIds":[],"ReviewStatistics":{"TotalReviewCount":1,"RecommendedCount":0,"HelpfulVoteCount":0,"FeaturedReviewCount":0,"RatingDistribution":[{"RatingValue":5,"Count":1}],"NotHelpfulVoteCount":0,"RatingsOnlyReviewCount":0,"NotRecommendedCount":0,"FirstSubmissionTime":"2018-07-23T22:32:09.000+00:00","LastSubmissionTime":"2018-07-23T22:32:09.000+00:00","AverageOverallRating":5.0,"ContextDataDistribution":{},"ContextDataDistributionOrder":[],"SecondaryRatingsAveragesOrder":[],"TagDistributionOrder":[],"SecondaryRatingsAverages":{},"TagDistribution":{},"OverallRatingRange":5},"TotalReviewCount":1,"FilteredReviewStatistics":{"TotalReviewCount":1,"RecommendedCount":0,"HelpfulVoteCount":0,"FeaturedReviewCount":0,"RatingDistribution":[{"RatingValue":5,"Count":1}],"NotHelpfulVoteCount":0,"RatingsOnlyReviewCount":0,"NotRecommendedCount":0,"FirstSubmissionTime":"2018-07-23T22:32:09.000+00:00","LastSubmissionTime":"2018-07-23T22:32:09.000+00:00","AverageOverallRating":5.0,"ContextDataDistribution":{},"ContextDataDistributionOrder":[],"SecondaryRatingsAveragesOrder":[],"TagDistributionOrder":[],"SecondaryRatingsAverages":{},"TagDistribution":{},"OverallRatingRange":5}},"2y5ed8gz3j5wmevyph00mulkw":{"Id":"2y5ed8gz3j5wmevyph00mulkw","ContributorRank":"NONE","UserNickname":"Aimee","LastModeratedTime":"2018-07-23T13:32:01.000+00:00","ModerationStatus":"APPROVED","SubmissionTime":"2018-07-23T13:08:30.000+00:00","ThirdPartyIds":[],"Location":null,"ContextDataValuesOrder":[],"Avatar":{},"ContextDataValues":{},"ProductRecommendationIds":[],"CommentIds":[],"StoryIds":[],"QuestionIds":[],"ReviewIds":[],"Badges":{},"AdditionalFields":{},"Photos":[],"SecondaryRatings":{},"SecondaryRatingsOrder":[],"SubmissionId":null,"BadgesOrder":[],"AdditionalFieldsOrder":[],"Videos":[],"AnswerIds":[],"ReviewStatistics":{"AverageOverallRating":4.0,"NotRecommendedCount":0,"RatingsOnlyReviewCount":0,"RecommendedCount":0,"RatingDistribution":[{"RatingValue":4,"Count":3}],"HelpfulVoteCount":0,"FirstSubmissionTime":"2018-07-23T13:08:30.000+00:00","LastSubmissionTime":"2018-07-23T13:09:36.000+00:00","FeaturedReviewCount":0,"NotHelpfulVoteCount":0,"TotalReviewCount":3,"ContextDataDistribution":{},"ContextDataDistributionOrder":[],"SecondaryRatingsAveragesOrder":[],"TagDistributionOrder":[],"SecondaryRatingsAverages":{},"TagDistribution":{},"OverallRatingRange":5},"TotalReviewCount":3,"FilteredReviewStatistics":{"AverageOverallRating":4.0,"NotRecommendedCount":0,"RatingsOnlyReviewCount":0,"RecommendedCount":0,"RatingDistribution":[{"RatingValue":4,"Count":1}],"HelpfulVoteCount":0,"FirstSubmissionTime":"2018-07-23T13:08:30.000+00:00","LastSubmissionTime":"2018-07-23T13:08:30.000+00:00","FeaturedReviewCount":0,"NotHelpfulVoteCount":0,"TotalReviewCount":1,"ContextDataDistribution":{},"ContextDataDistributionOrder":[],"SecondaryRatingsAveragesOrder":[],"TagDistributionOrder":[],"SecondaryRatingsAverages":{},"TagDistribution":{},"OverallRatingRange":5}},"77khuatdrl5iaxnrs4r2jza3b":{"Id":"77khuatdrl5iaxnrs4r2jza3b","ContributorRank":"NONE","UserNickname":"Mel","LastModeratedTime":"2018-07-11T00:00:34.000+00:00","ModerationStatus":"APPROVED","SubmissionTime":"2018-07-10T23:33:45.000+00:00","ThirdPartyIds":[],"Location":null,"ContextDataValuesOrder":[],"Avatar":{},"ContextDataValues":{},"ProductRecommendationIds":[],"CommentIds":[],"StoryIds":[],"QuestionIds":[],"ReviewIds":[],"Badges":{},"AdditionalFields":{},"Photos":[],"SecondaryRatings":{},"SecondaryRatingsOrder":[],"SubmissionId":null,"BadgesOrder":[],"AdditionalFieldsOrder":[],"Videos":[],"AnswerIds":[],"ReviewStatistics":{"RatingsOnlyReviewCount":0,"NotRecommendedCount":0,"HelpfulVoteCount":0,"FirstSubmissionTime":"2018-07-10T23:33:45.000+00:00","LastSubmissionTime":"2018-07-10T23:35:41.000+00:00","AverageOverallRating":5.0,"NotHelpfulVoteCount":0,"TotalReviewCount":3,"RecommendedCount":0,"FeaturedReviewCount":0,"RatingDistribution":[{"RatingValue":5,"Count":3}],"ContextDataDistribution":{},"ContextDataDistributionOrder":[],"SecondaryRatingsAveragesOrder":[],"TagDistributionOrder":[],"SecondaryRatingsAverages":{},"TagDistribution":{},"OverallRatingRange":5},"TotalReviewCount":3,"FilteredReviewStatistics":{"RatingsOnlyReviewCount":0,"NotRecommendedCount":0,"HelpfulVoteCount":0,"FirstSubmissionTime":"2018-07-10T23:35:41.000+00:00","LastSubmissionTime":"2018-07-10T23:35:41.000+00:00","AverageOverallRating":5.0,"NotHelpfulVoteCount":0,"TotalReviewCount":1,"RecommendedCount":0,"FeaturedReviewCount":0,"RatingDistribution":[{"RatingValue":5,"Count":1}],"ContextDataDistribution":{},"ContextDataDistributionOrder":[],"SecondaryRatingsAveragesOrder":[],"TagDistributionOrder":[],"SecondaryRatingsAverages":{},"TagDistribution":{},"OverallRatingRange":5}},"aiggomw1u9u1x2x6cbn5odfdo":{"Id":"aiggomw1u9u1x2x6cbn5odfdo","ContributorRank":"NONE","UserNickname":"DRSWIM","LastModeratedTime":"2018-07-29T02:30:47.000+00:00","ModerationStatus":"APPROVED","SubmissionTime":"2018-07-27T18:20:43.000+00:00","ThirdPartyIds":[],"Location":null,"ContextDataValuesOrder":[],"Avatar":{},"ContextDataValues":{},"ProductRecommendationIds":[],"CommentIds":[],"StoryIds":[],"QuestionIds":[],"ReviewIds":[],"Badges":{},"AdditionalFields":{},"Photos":[],"SecondaryRatings":{},"SecondaryRatingsOrder":[],"SubmissionId":null,"BadgesOrder":[],"AdditionalFieldsOrder":[],"Videos":[],"AnswerIds":[],"ReviewStatistics":{"FeaturedReviewCount":0,"RecommendedCount":0,"AverageOverallRating":2.5,"RatingsOnlyReviewCount":0,"TotalReviewCount":2,"HelpfulVoteCount":0,"NotRecommendedCount":0,"RatingDistribution":[{"RatingValue":2,"Count":1},{"RatingValue":3,"Count":1}],"FirstSubmissionTime":"2018-07-27T18:20:43.000+00:00","LastSubmissionTime":"2018-07-27T21:35:54.000+00:00","NotHelpfulVoteCount":0,"ContextDataDistribution":{},"ContextDataDistributionOrder":[],"SecondaryRatingsAveragesOrder":[],"TagDistributionOrder":[],"SecondaryRatingsAverages":{},"TagDistribution":{},"OverallRatingRange":5},"TotalReviewCount":2,"FilteredReviewStatistics":{"FeaturedReviewCount":0,"RecommendedCount":0,"AverageOverallRating":2.0,"RatingsOnlyReviewCount":0,"TotalReviewCount":1,"HelpfulVoteCount":0,"NotRecommendedCount":0,"RatingDistribution":[{"RatingValue":2,"Count":1}],"FirstSubmissionTime":"2018-07-27T21:35:54.000+00:00","LastSubmissionTime":"2018-07-27T21:35:54.000+00:00","NotHelpfulVoteCount":0,"ContextDataDistribution":{},"ContextDataDistributionOrder":[],"SecondaryRatingsAveragesOrder":[],"TagDistributionOrder":[],"SecondaryRatingsAverages":{},"TagDistribution":{},"OverallRatingRange":5}},"tusc7uv87cctc7sra0ukq8oq7":{"Id":"tusc7uv87cctc7sra0ukq8oq7","ContributorRank":"NONE","UserNickname":"jma5012","LastModeratedTime":"2018-07-03T15:30:34.000+00:00","ModerationStatus":"APPROVED","SubmissionTime":"2018-07-03T15:00:52.000+00:00","ThirdPartyIds":[],"Location":null,"ContextDataValuesOrder":[],"Avatar":{},"ContextDataValues":{},"ProductRecommendationIds":[],"CommentIds":[],"StoryIds":[],"QuestionIds":[],"ReviewIds":[],"Badges":{},"AdditionalFields":{},"Photos":[],"SecondaryRatings":{},"SecondaryRatingsOrder":[],"SubmissionId":null,"BadgesOrder":[],"AdditionalFieldsOrder":[],"Videos":[],"AnswerIds":[],"ReviewStatistics":{"TotalReviewCount":2,"RatingsOnlyReviewCount":0,"RatingDistribution":[{"RatingValue":5,"Count":2}],"FirstSubmissionTime":"2018-07-03T15:00:52.000+00:00","LastSubmissionTime":"2018-07-03T15:00:56.000+00:00","NotHelpfulVoteCount":0,"AverageOverallRating":5.0,"FeaturedReviewCount":0,"RecommendedCount":0,"NotRecommendedCount":0,"HelpfulVoteCount":0,"ContextDataDistribution":{},"ContextDataDistributionOrder":[],"SecondaryRatingsAveragesOrder":[],"TagDistributionOrder":[],"SecondaryRatingsAverages":{},"TagDistribution":{},"OverallRatingRange":5},"TotalReviewCount":2,"FilteredReviewStatistics":{"TotalReviewCount":1,"RatingsOnlyReviewCount":0,"RatingDistribution":[{"RatingValue":5,"Count":1}],"FirstSubmissionTime":"2018-07-03T15:00:52.000+00:00","LastSubmissionTime":"2018-07-03T15:00:52.000+00:00","NotHelpfulVoteCount":0,"AverageOverallRating":5.0,"FeaturedReviewCount":0,"RecommendedCount":0,"NotRecommendedCount":0,"HelpfulVoteCount":0,"ContextDataDistribution":{},"ContextDataDistributionOrder":[],"SecondaryRatingsAveragesOrder":[],"TagDistributionOrder":[],"SecondaryRatingsAverages":{},"TagDistribution":{},"OverallRatingRange":5}},"2z1qcs90l4n47jg6tockm6gr7":{"Id":"2z1qcs90l4n47jg6tockm6gr7","ContributorRank":"NONE","UserNickname":"Vero","LastModeratedTime":"2018-07-19T05:15:34.000+00:00","ModerationStatus":"APPROVED","SubmissionTime":"2018-07-19T04:25:22.000+00:00","ThirdPartyIds":[],"Location":null,"ContextDataValuesOrder":[],"Avatar":{},"ContextDataValues":{},"ProductRecommendationIds":[],"CommentIds":[],"StoryIds":[],"QuestionIds":[],"ReviewIds":[],"Badges":{},"AdditionalFields":{},"Photos":[],"SecondaryRatings":{},"SecondaryRatingsOrder":[],"SubmissionId":null,"BadgesOrder":[],"AdditionalFieldsOrder":[],"Videos":[],"AnswerIds":[],"ReviewStatistics":{"RecommendedCount":0,"HelpfulVoteCount":0,"RatingDistribution":[{"RatingValue":5,"Count":3}],"FeaturedReviewCount":0,"AverageOverallRating":5.0,"RatingsOnlyReviewCount":0,"TotalReviewCount":3,"NotHelpfulVoteCount":0,"NotRecommendedCount":0,"FirstSubmissionTime":"2018-07-19T04:25:22.000+00:00","LastSubmissionTime":"2018-07-19T04:26:20.000+00:00","ContextDataDistribution":{},"ContextDataDistributionOrder":[],"SecondaryRatingsAveragesOrder":[],"TagDistributionOrder":[],"SecondaryRatingsAverages":{},"TagDistribution":{},"OverallRatingRange":5},"TotalReviewCount":3,"FilteredReviewStatistics":{"RecommendedCount":0,"HelpfulVoteCount":0,"RatingDistribution":[{"RatingValue":5,"Count":1}],"FeaturedReviewCount":0,"AverageOverallRating":5.0,"RatingsOnlyReviewCount":0,"TotalReviewCount":1,"NotHelpfulVoteCount":0,"NotRecommendedCount":0,"FirstSubmissionTime":"2018-07-19T04:26:20.000+00:00","LastSubmissionTime":"2018-07-19T04:26:20.000+00:00","ContextDataDistribution":{},"ContextDataDistributionOrder":[],"SecondaryRatingsAveragesOrder":[],"TagDistributionOrder":[],"SecondaryRatingsAverages":{},"TagDistribution":{},"OverallRatingRange":5}},"62u4k7jxygii6ykb93n5eg0r3":{"Id":"62u4k7jxygii6ykb93n5eg0r3","Location":"Delaware","ContributorRank":"NONE","UserNickname":"TrayDiva","LastModeratedTime":"2018-07-14T14:15:23.000+00:00","ModerationStatus":"APPROVED","SubmissionTime":"2018-07-14T13:50:33.000+00:00","ThirdPartyIds":[],"ContextDataValuesOrder":[],"Avatar":{},"ContextDataValues":{},"ProductRecommendationIds":[],"CommentIds":[],"StoryIds":[],"QuestionIds":[],"ReviewIds":[],"Badges":{},"AdditionalFields":{},"Photos":[],"SecondaryRatings":{},"SecondaryRatingsOrder":[],"SubmissionId":null,"BadgesOrder":[],"AdditionalFieldsOrder":[],"Videos":[],"AnswerIds":[],"ReviewStatistics":{"NotHelpfulVoteCount":0,"AverageOverallRating":5.0,"RecommendedCount":0,"TotalReviewCount":1,"NotRecommendedCount":0,"HelpfulVoteCount":0,"FirstSubmissionTime":"2018-07-14T13:50:33.000+00:00","LastSubmissionTime":"2018-07-14T13:50:33.000+00:00","RatingsOnlyReviewCount":0,"FeaturedReviewCount":0,"RatingDistribution":[{"RatingValue":5,"Count":1}],"ContextDataDistribution":{},"ContextDataDistributionOrder":[],"SecondaryRatingsAveragesOrder":[],"TagDistributionOrder":[],"SecondaryRatingsAverages":{},"TagDistribution":{},"OverallRatingRange":5},"TotalReviewCount":1,"FilteredReviewStatistics":{"NotHelpfulVoteCount":0,"AverageOverallRating":5.0,"RecommendedCount":0,"TotalReviewCount":1,"NotRecommendedCount":0,"HelpfulVoteCount":0,"FirstSubmissionTime":"2018-07-14T13:50:33.000+00:00","LastSubmissionTime":"2018-07-14T13:50:33.000+00:00","RatingsOnlyReviewCount":0,"FeaturedReviewCount":0,"RatingDistribution":[{"RatingValue":5,"Count":1}],"ContextDataDistribution":{},"ContextDataDistributionOrder":[],"SecondaryRatingsAveragesOrder":[],"TagDistributionOrder":[],"SecondaryRatingsAverages":{},"TagDistribution":{},"OverallRatingRange":5}},"smmfthok4rjpfearkyaxve1ls":{"Id":"smmfthok4rjpfearkyaxve1ls","ContributorRank":"NONE","UserNickname":"handgsmom","LastModeratedTime":"2018-07-10T15:00:19.000+00:00","ModerationStatus":"APPROVED","SubmissionTime":"2018-07-10T12:32:25.000+00:00","ThirdPartyIds":[],"Location":null,"ContextDataValuesOrder":[],"Avatar":{},"ContextDataValues":{},"ProductRecommendationIds":[],"CommentIds":[],"StoryIds":[],"QuestionIds":[],"ReviewIds":[],"Badges":{},"AdditionalFields":{},"Photos":[],"SecondaryRatings":{},"SecondaryRatingsOrder":[],"SubmissionId":null,"BadgesOrder":[],"AdditionalFieldsOrder":[],"Videos":[],"AnswerIds":[],"ReviewStatistics":{"FeaturedReviewCount":0,"NotHelpfulVoteCount":0,"RecommendedCount":0,"RatingDistribution":[{"RatingValue":5,"Count":2}],"NotRecommendedCount":0,"HelpfulVoteCount":0,"FirstSubmissionTime":"2018-07-06T01:33:19.000+00:00","LastSubmissionTime":"2018-07-10T12:32:25.000+00:00","RatingsOnlyReviewCount":0,"AverageOverallRating":5.0,"TotalReviewCount":2,"ContextDataDistribution":{},"ContextDataDistributionOrder":[],"SecondaryRatingsAveragesOrder":[],"TagDistributionOrder":[],"SecondaryRatingsAverages":{},"TagDistribution":{},"OverallRatingRange":5},"TotalReviewCount":2,"FilteredReviewStatistics":{"FeaturedReviewCount":0,"NotHelpfulVoteCount":0,"RecommendedCount":0,"RatingDistribution":[{"RatingValue":5,"Count":1}],"NotRecommendedCount":0,"HelpfulVoteCount":0,"FirstSubmissionTime":"2018-07-10T12:32:25.000+00:00","LastSubmissionTime":"2018-07-10T12:32:25.000+00:00","RatingsOnlyReviewCount":0,"AverageOverallRating":5.0,"TotalReviewCount":1,"ContextDataDistribution":{},"ContextDataDistributionOrder":[],"SecondaryRatingsAveragesOrder":[],"TagDistributionOrder":[],"SecondaryRatingsAverages":{},"TagDistribution":{},"OverallRatingRange":5}}},"AuthorsOrder":["tusc7uv87cctc7sra0ukq8oq7","smmfthok4rjpfearkyaxve1ls","qe5q7mh5nsafe4b5zfxxlg64v","aiggomw1u9u1x2x6cbn5odfdo","aaggas0cameq9f7ohzs0h8arc","77khuatdrl5iaxnrs4r2jza3b","6t395zv4ggp2k123pq59z0mw2","62u4k7jxygii6ykb93n5eg0r3","2z1qcs90l4n47jg6tockm6gr7","2y5ed8gz3j5wmevyph00mulkw"]},"HasErrors":false,"Errors":[]},"q0":{"Id":"q0","Limit":10,"Offset":0,"TotalResults":1,"Locale":"en_US","Results":[{"FamilyIds":["205434"],"AttributesOrder":["SEASON_YEAR","SEASON_CODE","BV_FE_EXPAND","BV_FE_FAMILY"],"Attributes":{"SEASON_YEAR":{"Id":"SEASON_YEAR","Values":[{"Value":"2018","Locale":null}]},"SEASON_CODE":{"Id":"SEASON_CODE","Values":[{"Value":"M07","Locale":null}]},"BV_FE_EXPAND":{"Id":"BV_FE_EXPAND","Values":[{"Value":"BV_FE_FAMILY:205434","Locale":null}]},"BV_FE_FAMILY":{"Id":"BV_FE_FAMILY","Values":[{"Value":"205434","Locale":null}]}},"Description":"Classic Sunglasses for Men","ImageUrl":"http://oldnavy.gap.com/resources/productImage/v1/205434002/VI","Name":"Classic Sunglasses for Men  (Blackjack)","Id":"205434002","CategoryId":"205434","BrandExternalId":"3","Brand":{"Id":"3","Name":"OLD NAVY"},"Active":true,"ProductPageUrl":"http://oldnavy.gap.com/browse/product.do?pid=205434002&locale=en_US","Disabled":false,"StoryIds":[],"EANs":[],"ManufacturerPartNumbers":[],"QuestionIds":[],"UPCs":[],"ISBNs":[],"ReviewIds":[],"ModelNumbers":[],"ReviewStatistics":{"AverageOverallRating":4.480769230769231,"NotHelpfulVoteCount":0,"TotalReviewCount":52,"ContextDataDistributionOrder":["IncentivizedReview"],"ContextDataDistribution":{"IncentivizedReview":{"Id":"IncentivizedReview","Values":[{"Count":48,"Value":"True"}]}},"RatingsOnlyReviewCount":8,"FeaturedReviewCount":0,"FirstSubmissionTime":"2018-03-06T03:48:36.000+00:00","LastSubmissionTime":"2018-08-05T02:02:52.000+00:00","NotRecommendedCount":0,"RatingDistribution":[{"RatingValue":5,"Count":37},{"RatingValue":4,"Count":9},{"RatingValue":1,"Count":2},{"RatingValue":2,"Count":2},{"RatingValue":3,"Count":2}],"RecommendedCount":0,"HelpfulVoteCount":3,"SecondaryRatingsAveragesOrder":[],"TagDistributionOrder":[],"SecondaryRatingsAverages":{},"TagDistribution":{},"OverallRatingRange":5},"TotalReviewCount":52,"FilteredReviewStatistics":{"AverageOverallRating":4.480769230769231,"NotHelpfulVoteCount":0,"TotalReviewCount":52,"ContextDataDistributionOrder":["IncentivizedReview"],"ContextDataDistribution":{"IncentivizedReview":{"Id":"IncentivizedReview","Values":[{"Count":48,"Value":"True"}]}},"RatingsOnlyReviewCount":8,"FeaturedReviewCount":0,"FirstSubmissionTime":"2018-03-06T03:48:36.000+00:00","LastSubmissionTime":"2018-08-05T02:02:52.000+00:00","NotRecommendedCount":0,"RatingDistribution":[{"RatingValue":5,"Count":37},{"RatingValue":4,"Count":9},{"RatingValue":1,"Count":2},{"RatingValue":2,"Count":2},{"RatingValue":3,"Count":2}],"RecommendedCount":0,"HelpfulVoteCount":3,"SecondaryRatingsAveragesOrder":[],"TagDistributionOrder":[],"SecondaryRatingsAverages":{},"TagDistribution":{},"OverallRatingRange":5}}],"Includes":{},"HasErrors":false,"Errors":[]}},"SuccessfulRequests":2,"FailedRequests":0}